syspop/__init__.py
syspop/run_nz.py
syspop/syspop.py
syspop/process/__init__.py
syspop/process/address.py
syspop/process/base_pop.py
syspop/process/commute.py
syspop/process/create_pop_wrapper.py
syspop/process/diary.py
syspop/process/hospital.py
syspop/process/household.py
syspop/process/school.py
syspop/process/shared_space.py
syspop/process/social_economic.py
syspop/process/utils.py
syspop/process/validate.py
syspop/process/vis.py
syspop/process/work.py
syspop/process/var/__init__.py
syspop/process/var/validate.py
syspop/process/var/var.py
syspop-0.2.1.dist-info/METADATA
syspop-0.2.1.dist-info/WHEEL
syspop-0.2.1.dist-info/entry_points.txt
syspop-0.2.1.dist-info/top_level.txt
syspop-0.2.1.dist-info/RECORD
