Metadata-Version: 2.1
Name: syspop
Version: 0.2.1
Requires-Dist: numpy
Requires-Dist: pandas
Requires-Dist: matplotlib
Requires-Dist: pyarrow
Requires-Dist: overpy
Requires-Dist: geopy
Requires-Dist: scipy
Requires-Dist: shapely
Requires-Dist: openpyxl
Requires-Dist: ray[default]
Requires-Dist: xlrd
Requires-Dist: OSMPythonTools
Requires-Dist: folium
Requires-Dist: seaborn
Requires-Dist: geopandas
